omegavit/__init__.py
omegavit/main.py
omegavit-0.0.1.dist-info/LICENSE
omegavit-0.0.1.dist-info/METADATA
omegavit-0.0.1.dist-info/WHEEL
omegavit-0.0.1.dist-info/RECORD
