Metadata-Version: 2.1
Name: omegavit
Version: 0.0.1
Summary: OmegaViT: A State-of-the-Art Vision Transformer with Multi-Query Attention, State Space Modeling, and Mixture of Experts
Home-page: https://github.com/Agora-Lab-AI/OmegaViT
License: MIT
Keywords: artificial intelligence,deep learning,optimizers,Prompt Engineering
Author: Kye Gomez
Author-email: kye@apac.ai
Requires-Python: >=3.10,<4.0
Classifier: Development Status :: 4 - Beta
Classifier: Intended Audience :: Developers
Classifier: License :: OSI Approved :: MIT License
Classifier: Programming Language :: Python :: 3
Classifier: Programming Language :: Python :: 3.10
Classifier: Programming Language :: Python :: 3.11
Classifier: Programming Language :: Python :: 3.12
Classifier: Programming Language :: Python :: 3.9
Classifier: Topic :: Scientific/Engineering :: Artificial Intelligence
Requires-Dist: einops
Requires-Dist: loguru
Requires-Dist: torch
Project-URL: Documentation, https://github.com/Agora-Lab-AI/OmegaViT
Project-URL: Repository, https://github.com/Agora-Lab-AI/OmegaViT
